CHANGELOG.rst
LICENSE.rst
MANIFEST.in
README.rst
setup.py
incoming/__init__.py
incoming/compat.py
incoming/datatypes.py
incoming/incoming.py
incoming.egg-info/PKG-INFO
incoming.egg-info/SOURCES.txt
incoming.egg-info/dependency_links.txt
incoming.egg-info/not-zip-safe
incoming.egg-info/top_level.txt
incoming/tests/__init__.py
incoming/tests/test_datatypes.py
incoming/tests/test_incoming.py