Metadata-Version: 1.1
Name: incoming
Version: 0.3.1
Summary: JSON validation framework for Python.
Home-page: https://github.com/vaidik/incoming
Author: Vaidik Kapoor
Author-email: kapoor.vaidik@gmail.com
License: UNKNOWN
Platform: UNKNOWN
Classifier: Programming Language :: Python
Classifier: Development Status :: 1 - Planning
Classifier: Intended Audience :: Developers
Classifier: License :: OSI Approved :: MIT License
